{
  "scenario.ascesa-aurion.name": "Ascesa di Aurion",
  "scenario.ascesa-aurion.description": "Sei alla guida di Aurion, una piccola repubblica industriale incastonata sulla penisola di Auriana. Stretta tra ambizioni delle grandi potenze e l'ombra della Federazione Borea, hai una sola occasione per trasformare il tuo paese in una nazione che il mondo non potrà più ignorare.",

  "country.aurion.name": "Aurion",
  "country.aurion.capital": "Auronia",
  "country.velmara.name": "Velmara",
  "country.velmara.capital": "Cala Velmar",
  "country.korthia.name": "Korthia",
  "country.korthia.capital": "Korthopoli",
  "country.sundria.name": "Sundria",
  "country.sundria.capital": "Porto Sundra",
  "country.federazione-borea.name": "Federazione Borea",
  "country.federazione-borea.capital": "Vyrgrad",
  "country.tundria.name": "Tundria",
  "country.tundria.capital": "Karelvik",
  "country.norhavn.name": "Norhavn",
  "country.norhavn.capital": "Eldfjord",
  "country.rusvenia.name": "Rusvenia",
  "country.rusvenia.capital": "Velikograd",
  "country.iskal.name": "Iskal",
  "country.iskal.capital": "Sjorholm",
  "country.calanthia.name": "Calanthia",
  "country.calanthia.capital": "Tehuanca",
  "country.xanaba.name": "Xanaba",
  "country.xanaba.capital": "Itzkali",
  "country.yureka.name": "Yureka",
  "country.yureka.capital": "Sarnapur",
  "country.verdantia.name": "Verdantia",
  "country.verdantia.capital": "Selva Mayor",
  "country.tolmek.name": "Tolmek",
  "country.tolmek.capital": "Cuapan",
  "country.tenshido.name": "Tenshido",
  "country.tenshido.capital": "Kanaru",
  "country.hakaria.name": "Hakaria",
  "country.hakaria.capital": "Yurosh",
  "country.mireku.name": "Mireku",
  "country.mireku.capital": "Atosima",
  "country.aolan.name": "Aolan",
  "country.aolan.capital": "Vongdo",
  "country.sankai.name": "Sankai",
  "country.sankai.capital": "Hosanto",
  "country.pelagia.name": "Pelagia",
  "country.pelagia.capital": "Marivola",
  "country.karoun.name": "Karoun",
  "country.karoun.capital": "Al-Mahrash",
  "country.saharel.name": "Saharel",
  "country.saharel.capital": "Tinassir",
  "country.mokshara.name": "Mokshara",
  "country.mokshara.capital": "Beit-Nahar",
  "country.zembu.name": "Zembu",
  "country.zembu.capital": "Mwasanga",
  "country.antarah.name": "Antarah",
  "country.antarah.capital": "Qasr al-Bahr",

  "tech.civil.irrigation.name": "Irrigazione moderna",
  "tech.civil.irrigation.description": "Reti di canali e pompe a basso costo aumentano la produttività agricola del 15% e stabilizzano i raccolti.",
  "tech.civil.tax_reform.name": "Riforma fiscale",
  "tech.civil.tax_reform.description": "Una nuova amministrazione semplificata raccoglie più gettito riducendo l'evasione e sblocca audit mirati.",
  "tech.civil.public_health.name": "Sanità pubblica",
  "tech.civil.public_health.description": "Cliniche di base e vaccinazioni di massa migliorano l'aspettativa di vita e fanno crescere la popolarità del governo.",
  "tech.civil.urbanization.name": "Urbanizzazione pianificata",
  "tech.civil.urbanization.description": "Piani regolatori per le città in espansione potenziano il settore servizi e aumentano il PIL complessivo.",
  "tech.civil.automated_factories.name": "Fabbriche automatizzate",
  "tech.civil.automated_factories.description": "Linee robotizzate e gestione informatica della produzione spingono in alto il settore industriale.",
  "tech.civil.education_reform.name": "Riforma scolastica",
  "tech.civil.education_reform.description": "Università pubbliche di nuova generazione formano scienziati e ingegneri, accelerando ricerca e settore tech.",
  "tech.civil.green_energy.name": "Energia verde",
  "tech.civil.green_energy.description": "Eolico, solare e nuove reti riducono i costi energetici e ti rendono popolare presso i cittadini.",
  "tech.civil.high_speed_rail.name": "Alta velocità ferroviaria",
  "tech.civil.high_speed_rail.description": "Connessioni rapide tra le città principali liberano traffici, abitudini e produttività dei servizi.",
  "tech.civil.biotechnology.name": "Biotecnologia avanzata",
  "tech.civil.biotechnology.description": "Genomica, terapie cellulari e nuovi materiali biologici alimentano un'industria tech ad altissimo margine.",
  "tech.civil.smart_cities.name": "Smart cities",
  "tech.civil.smart_cities.description": "Città iperconnesse, traffico ottimizzato e servizi digitali ovunque: efficienza enorme e cittadini soddisfatti.",
  "tech.civil.post_scarcity.name": "Economia post-scarsità",
  "tech.civil.post_scarcity.description": "Automazione totale e fusione fredda sperimentale promettono abbondanza diffusa e una nuova era industriale.",

  "tech.military.modern_doctrine.name": "Dottrina militare moderna",
  "tech.military.modern_doctrine.description": "Riforma di addestramento e catena di comando: le tue unità diventano più reattive e meglio coordinate.",
  "tech.military.precision_artillery.name": "Artiglieria di precisione",
  "tech.military.precision_artillery.description": "Munizioni guidate e radar di tiro: meno colpi sprecati, più colpi dove servono.",
  "tech.military.armored_navy.name": "Marina corazzata",
  "tech.military.armored_navy.description": "Nuove fregate e cacciatorpediniere con corazzature composite ridisegnano il rapporto di forza in mare.",
  "tech.military.air_superiority.name": "Superiorità aerea",
  "tech.military.air_superiority.description": "Caccia di nuova generazione e radar di scoperta avanzati ti danno un vantaggio decisivo nei cieli.",
  "tech.military.combined_arms.name": "Armi combinate",
  "tech.military.combined_arms.description": "Operazioni integrate tra fanteria, artiglieria e aria: dottrina rivoluzionata.",
  "tech.military.drones.name": "Droni da combattimento",
  "tech.military.drones.description": "UAV armati e ricognitori autonomi moltiplicano la portata della tua aviazione a basso costo.",
  "tech.military.carrier_groups.name": "Gruppi portaerei",
  "tech.military.carrier_groups.description": "Portaerei moderne con scorte integrate proiettano la tua forza ovunque ci sia mare.",
  "tech.military.integrated_command.name": "Comando integrato",
  "tech.military.integrated_command.description": "Centri operativi unificati orchestrano in tempo reale tutte le forze sul campo.",
  "tech.military.cyber_warfare.name": "Guerra cibernetica",
  "tech.military.cyber_warfare.description": "Unità offensive nel cyberspazio sabotano comandi nemici e proteggono le tue reti critiche.",
  "tech.military.hypersonic_missiles.name": "Missili ipersonici",
  "tech.military.hypersonic_missiles.description": "Vettori a Mach 5+ rendono inefficaci i sistemi di difesa missilistica avversari.",
  "tech.military.autonomous_warfare.name": "Guerra autonoma",
  "tech.military.autonomous_warfare.description": "Sciami di droni e mezzi senza pilota condotti da IA ridefiniscono il campo di battaglia.",

  "tech.intel.counter_intel.name": "Controspionaggio",
  "tech.intel.counter_intel.description": "Reti di sorveglianza interna e protocolli rinforzati rendono più difficile per le spie nemiche operare nel tuo paese.",
  "tech.intel.cryptography.name": "Crittografia avanzata",
  "tech.intel.cryptography.description": "Cifrari quasi inviolabili proteggono le comunicazioni e abilitano le operazioni di furto tecnologico.",
  "tech.intel.agent_training.name": "Addestramento agenti",
  "tech.intel.agent_training.description": "Una nuova accademia per i servizi segreti raddoppia il numero di agenti disponibili.",
  "tech.intel.mass_propaganda.name": "Propaganda di massa",
  "tech.intel.mass_propaganda.description": "Tecniche moderne di influenza ti permettono di lanciare campagne di propaganda nelle nazioni straniere.",
  "tech.intel.sleeper_cells.name": "Cellule dormienti",
  "tech.intel.sleeper_cells.description": "Reti di agenti infiltrati per anni nelle nazioni nemiche, pronti ad attivarsi per destabilizzare.",
  "tech.intel.signals_intelligence.name": "Intelligence dei segnali",
  "tech.intel.signals_intelligence.description": "Stazioni di intercettazione e analisi del traffico catturano comunicazioni nemiche su larga scala.",
  "tech.intel.wet_operations.name": "Operazioni nere",
  "tech.intel.wet_operations.description": "Sabotaggio e operazioni mirate diventano parte del repertorio dei tuoi servizi.",
  "tech.intel.global_network.name": "Rete globale",
  "tech.intel.global_network.description": "I tuoi servizi diventano una presenza permanente in ogni capitale del mondo.",
  "tech.intel.quantum_decryption.name": "Decrittazione quantistica",
  "tech.intel.quantum_decryption.description": "Computer quantistici sperimentali infrangono la crittografia avversaria: nessun segreto è più al sicuro.",

  "tech.space.weather_satellites.name": "Satelliti meteorologici",
  "tech.space.weather_satellites.description": "Una piccola costellazione orbitale migliora previsioni e raccolti agricoli, oltre alla qualità della ricerca.",
  "tech.space.orbital_launch.name": "Lancio orbitale",
  "tech.space.orbital_launch.description": "Razzi vettori riutilizzabili rendono il tuo paese una potenza spaziale: l'orgoglio nazionale cresce.",
  "tech.space.communications_array.name": "Rete comunicazioni satellitari",
  "tech.space.communications_array.description": "Una flotta di satelliti dedicati ti dà comunicazioni indipendenti e protette.",
  "tech.space.orbital_station.name": "Stazione orbitale",
  "tech.space.orbital_station.description": "La prima stazione spaziale permanente: laboratori in microgravità accelerano la ricerca e infiammano i cittadini.",
  "tech.space.lunar_probe.name": "Sonda lunare",
  "tech.space.lunar_probe.description": "Una missione robotica sulla Luna: il mondo ti guarda con rispetto e i tuoi laboratori ne traggono vantaggio.",
  "tech.space.lunar_base.name": "Base lunare",
  "tech.space.lunar_base.description": "Avamposto permanente sulla superficie selenica: pochi paesi al mondo possono dire altrettanto.",
  "tech.space.deep_space_telescope.name": "Telescopio per lo spazio profondo",
  "tech.space.deep_space_telescope.description": "Un osservatorio orbitale rivoluziona astronomia e ricerca pura.",
  "tech.space.mars_mission.name": "Missione su Marte",
  "tech.space.mars_mission.description": "I primi astronauti calcano il pianeta rosso: un trionfo storico per Aurion.",
  "tech.space.mars_colony.name": "Colonia su Marte",
  "tech.space.mars_colony.description": "Una colonia umana autosufficiente su Marte: l'umanità diventa multiplanetaria, e tu l'hai resa possibile.",

  "event.diplomacy.border_incident.name": "Incidente di confine",
  "event.diplomacy.border_incident.description": "Una pattuglia korthiana ha attraversato la frontiera e si è scontrata con la nostra polizia di confine. I morti sono pochi ma i media stanno gridando alla provocazione.",
  "event.diplomacy.border_incident.choice.protest": "Protesta diplomatica formale",
  "event.diplomacy.border_incident.choice.ignore": "Ignora l'incidente",
  "event.diplomacy.border_incident.choice.negotiate": "Negozia un risarcimento privato",

  "event.diplomacy.borealis_pressure.name": "Pressione di Borea",
  "event.diplomacy.borealis_pressure.description": "L'ambasciatore della Federazione Borea chiede di ridimensionare le tue ambizioni regionali. La sua voce è cortese, le navi al largo molto meno.",
  "event.diplomacy.borealis_pressure.choice.submit": "Cedi alle richieste",
  "event.diplomacy.borealis_pressure.choice.defy": "Rispondi sfidando pubblicamente",
  "event.diplomacy.borealis_pressure.choice.seek_allies": "Cerca alleati a Oriana e Norhavn",

  "event.economy.resource_boom.name": "Scoperta di un giacimento",
  "event.economy.resource_boom.description": "I geologi hanno individuato un grande giacimento di terre rare nelle valli interne. Un'opportunità rara, ma le comunità locali sono già nervose.",
  "event.economy.resource_boom.choice.exploit_quickly": "Avvia l'estrazione subito",
  "event.economy.resource_boom.choice.long_term_plan": "Pianifica uno sfruttamento sostenibile",
  "event.economy.resource_boom.choice.public_trust": "Costituisci un fondo sovrano per i cittadini",

  "event.economy.financial_crisis.name": "Crisi di liquidità",
  "event.economy.financial_crisis.description": "Le casse dello Stato sono al limite e i creditori internazionali iniziano a fare domande scomode. Serve una decisione, e in fretta.",
  "event.economy.financial_crisis.choice.austerity": "Tagli drastici alla spesa pubblica",
  "event.economy.financial_crisis.choice.foreign_loan": "Accetta un prestito da Borea",
  "event.economy.financial_crisis.choice.print_money": "Stampa moneta per coprire il deficit",

  "event.social.protests.name": "Proteste di piazza",
  "event.social.protests.description": "Decine di migliaia di cittadini riempiono il centro di Auronia chiedendo riforme. La situazione è tesa ma non ancora violenta.",
  "event.social.protests.choice.crackdown": "Disperdi i manifestanti con la forza",
  "event.social.protests.choice.dialogue": "Apri un tavolo di dialogo pubblico",
  "event.social.protests.choice.ignore": "Lascia che si esauriscano da sole",

  "event.social.scandal.name": "Scandalo di corruzione",
  "event.social.scandal.description": "Un quotidiano d'opposizione ha pubblicato documenti che imbarazzano il tuo governo. Sui social la pressione cresce di ora in ora.",
  "event.social.scandal.choice.cover_up": "Soffoca la storia con denaro pubblico",
  "event.social.scandal.choice.transparency": "Avvia un'inchiesta indipendente",
  "event.social.scandal.choice.scapegoat": "Sacrifica un ministro come capro espiatorio",

  "event.social.terror_attack.name": "Attentato in capitale",
  "event.social.terror_attack.description": "Un'esplosione ha colpito un mercato di Auronia. Le vittime sono decine e le indagini puntano a una cellula proveniente dal Sahel-Karoun.",
  "event.social.terror_attack.choice.security_state": "Stato d'emergenza e nuovi poteri di sorveglianza",
  "event.social.terror_attack.choice.unity_call": "Discorso pubblico di unità nazionale",
  "event.social.terror_attack.choice.investigate_quietly": "Indagini riservate dei servizi all'estero",

  "event.military.defection.name": "Defezione di alto rango",
  "event.military.defection.description": "Un colonnello dello stato maggiore korthiano ha chiesto asilo politico portando con sé una valigetta di documenti riservati.",
  "event.military.defection.choice.welcome": "Accoglilo come rifugiato",
  "event.military.defection.choice.return": "Restituiscilo per un gesto di buona volontà",
  "event.military.defection.choice.exploit": "Sfrutta i documenti in segreto",

  "event.military.naval_clash.name": "Scontro navale in alto mare",
  "event.military.naval_clash.description": "Una nostra nave e una di Tenshido si sono sfiorate in acque contese. Qualcuno ha aperto il fuoco, e ora servono risposte.",
  "event.military.naval_clash.choice.escalate": "Rispondi con un'azione di forza",
  "event.military.naval_clash.choice.de_escalate": "Ritira le navi e chiedi chiarimenti",
  "event.military.naval_clash.choice.international_arbitration": "Porta il caso a un'arbitrato internazionale",

  "event.military.arms_offer.name": "Offerta di forniture militari",
  "event.military.arms_offer.description": "Sia Borea sia Tenshido offrono pacchetti d'armamento a condizioni favorevoli, in cambio di un riallineamento politico.",
  "event.military.arms_offer.choice.accept_borealis": "Accetta l'offerta di Borea",
  "event.military.arms_offer.choice.accept_tenshido": "Accetta l'offerta di Tenshido",
  "event.military.arms_offer.choice.refuse_both": "Rifiuta entrambe e mantieni indipendenza",

  "event.spy.caught_abroad.name": "Spia catturata all'estero",
  "event.spy.caught_abroad.description": "Una nostra agente è stata identificata e arrestata in territorio nemico. La stampa internazionale è impazzita.",
  "event.spy.caught_abroad.choice.disavow": "Negane ufficialmente l'esistenza",
  "event.spy.caught_abroad.choice.diplomatic_swap": "Negozia uno scambio di prigionieri",
  "event.spy.caught_abroad.choice.rescue_operation": "Autorizza un'operazione di estrazione",

  "event.spy.enemy_caught.name": "Agente nemico smascherato",
  "event.spy.enemy_caught.description": "Il controspionaggio ha individuato e catturato una spia korthiana attiva da mesi nel tuo paese. Adesso che ne fai?",
  "event.spy.enemy_caught.choice.public_expose": "Esponi pubblicamente il caso",
  "event.spy.enemy_caught.choice.turn_agent": "Trasformalo in agente doppio",
  "event.spy.enemy_caught.choice.silent_release": "Rilascialo in silenzio per favore diplomatico",

  "event.spy.blackmail.name": "Ricatto al ministro",
  "event.spy.blackmail.description": "Un'agenzia straniera è in possesso di materiale compromettente su un membro del tuo gabinetto e chiede concessioni in cambio del silenzio.",
  "event.spy.blackmail.choice.pay": "Paga il ricatto",
  "event.spy.blackmail.choice.expose_yourself": "Rendi pubblico tu stesso lo scandalo",
  "event.spy.blackmail.choice.eliminate_threat": "Risolvi il problema in modo definitivo",

  "event.spy.double_agent.name": "Sospetto agente doppio",
  "event.spy.double_agent.description": "Uno dei tuoi agenti più anziani potrebbe essere stato voltato dai servizi di Borea. Le prove sono incomplete.",
  "event.spy.double_agent.choice.feed_false_intel": "Usalo per veicolare disinformazione",
  "event.spy.double_agent.choice.eliminate": "Eliminalo immediatamente",
  "event.spy.double_agent.choice.recruit_back": "Convincilo a tornare dalla tua parte",

  "event.space.lost_probe.name": "Sonda perduta",
  "event.space.lost_probe.description": "Una nostra sonda ha smesso di trasmettere durante una manovra orbitale. Anni di lavoro a rischio.",
  "event.space.lost_probe.choice.retry": "Finanzia una seconda missione",
  "event.space.lost_probe.choice.cancel": "Cancella il programma e taglia le spese",
  "event.space.lost_probe.choice.international_partnership": "Cerca un partner internazionale",

  "event.space.breakthrough.name": "Scoperta scientifica",
  "event.space.breakthrough.description": "Esperimenti sulla stazione orbitale hanno prodotto un risultato inatteso e potenzialmente rivoluzionario.",
  "event.space.breakthrough.choice.publish": "Pubblicalo apertamente",
  "event.space.breakthrough.choice.classify": "Classifica i risultati come segreto militare",
  "event.space.breakthrough.choice.commercialize": "Cedilo a un consorzio industriale",

  "event.diplomacy.alliance_offer.name": "Proposta di alleanza",
  "event.diplomacy.alliance_offer.description": "Norhavn propone un patto di mutua difesa che potrebbe ridisegnare gli equilibri nel nord. Borea non gradirà.",
  "event.diplomacy.alliance_offer.choice.accept": "Accetta il patto",
  "event.diplomacy.alliance_offer.choice.counter_offer": "Proponi un trattato commerciale meno impegnativo",
  "event.diplomacy.alliance_offer.choice.refuse": "Rifiuta l'offerta",

  "event.diplomacy.summit_invite.name": "Invito a un summit",
  "event.diplomacy.summit_invite.description": "Calanthia organizza un vertice internazionale a Tehuanca. Tutti i grandi nomi saranno presenti.",
  "event.diplomacy.summit_invite.choice.attend": "Partecipa di persona",
  "event.diplomacy.summit_invite.choice.send_envoy": "Invia un ministro come delegato",
  "event.diplomacy.summit_invite.choice.boycott": "Boicotta il vertice pubblicamente",

  "event.economy.tech_sector_boom.name": "Boom del settore tech",
  "event.economy.tech_sector_boom.description": "I tuoi nuovi laureati stanno fondando start-up a ritmo vorticoso. Come accompagnare il fenomeno?",
  "event.economy.tech_sector_boom.choice.subsidize": "Sussidi diretti alle imprese innovative",
  "event.economy.tech_sector_boom.choice.tax_breaks": "Sconti fiscali per le aziende del settore",
  "event.economy.tech_sector_boom.choice.public_lab": "Fonda un laboratorio pubblico nazionale",

  "event.social.strike.name": "Sciopero generale",
  "event.social.strike.description": "I sindacati hanno proclamato uno sciopero di tre giorni che paralizzerà il paese. La mobilitazione è enorme.",
  "event.social.strike.choice.concede": "Concedi gli aumenti richiesti",
  "event.social.strike.choice.break_strike": "Forza i lavoratori a rientrare",
  "event.social.strike.choice.mediate": "Apri una mediazione tra le parti",

  "event.diplomacy.karoun_aggression.name": "Aggressione di Karoun",
  "event.diplomacy.karoun_aggression.description": "Karoun ha lanciato un'incursione militare contro Saharel. La comunità internazionale guarda a te per una posizione.",
  "event.diplomacy.karoun_aggression.choice.condemn": "Condanna pubblica e sostegno a Saharel",
  "event.diplomacy.karoun_aggression.choice.send_aid": "Invia aiuti umanitari a Saharel",
  "event.diplomacy.karoun_aggression.choice.stay_neutral": "Mantieni la neutralità",

  "event.economy.smuggling_ring.name": "Rete di contrabbando",
  "event.economy.smuggling_ring.description": "I servizi hanno individuato una rete che evade le dogane su scala industriale. Le ramificazioni toccano persone in vista.",
  "event.economy.smuggling_ring.choice.crack_down": "Smantellala con un'operazione massiccia",
  "event.economy.smuggling_ring.choice.tax_quietly": "Tassala in modo coperto attraverso intermediari",
  "event.economy.smuggling_ring.choice.recruit_informants": "Recluta i contrabbandieri come informatori",

  "event.social.religious_unrest.name": "Tensioni religiose",
  "event.social.religious_unrest.description": "Una serie di provocazioni nei confronti di una comunità religiosa minaccia di trasformarsi in disordini diffusi.",
  "event.social.religious_unrest.choice.appease": "Concessioni alla comunità religiosa",
  "event.social.religious_unrest.choice.secular_stance": "Difendi rigorosamente la laicità dello Stato",
  "event.social.religious_unrest.choice.invest_culture": "Investi in programmi culturali di dialogo",

  "event.military.recruitment_drive.name": "Campagna di arruolamento",
  "event.military.recruitment_drive.description": "Lo stato maggiore chiede di rinforzare gli effettivi. Quale strada vuoi seguire?",
  "event.military.recruitment_drive.choice.mass_conscription": "Coscrizione obbligatoria estesa",
  "event.military.recruitment_drive.choice.volunteer_call": "Campagna di reclutamento volontario",
  "event.military.recruitment_drive.choice.skip": "Rinvia il piano di rinforzi",

  "event.economy.trade_dispute.name": "Disputa commerciale",
  "event.economy.trade_dispute.description": "Tenshido accusa il tuo paese di pratiche scorrette e minaccia ritorsioni doganali sui beni industriali.",
  "event.economy.trade_dispute.choice.tariff": "Rispondi con tariffe punitive",
  "event.economy.trade_dispute.choice.subsidies": "Sussidi alle imprese colpite",
  "event.economy.trade_dispute.choice.negotiate_treaty": "Negozia un trattato commerciale",

  "event.intel.foreign_propaganda.name": "Propaganda straniera",
  "event.intel.foreign_propaganda.description": "Una campagna mediatica coordinata sta seminando dubbi sui tuoi cittadini. L'origine è quasi certamente esterna.",
  "event.intel.foreign_propaganda.choice.censor": "Censura le fonti sospette",
  "event.intel.foreign_propaganda.choice.counter_narrative": "Lancia una controcampagna informativa",
  "event.intel.foreign_propaganda.choice.ignore": "Lascia che sia l'opinione pubblica a decidere",

  "event.diplomacy.oriana_pact.name": "Patto di Oriana",
  "event.diplomacy.oriana_pact.description": "Tenshido propone un'organizzazione di cooperazione regionale nell'arcipelago orientale. Sei invitato come membro associato.",
  "event.diplomacy.oriana_pact.choice.join": "Aderisci come membro pieno",
  "event.diplomacy.oriana_pact.choice.observer": "Partecipa come osservatore",
  "event.diplomacy.oriana_pact.choice.decline": "Declina l'invito",

  "event.economy.industrial_accident.name": "Incidente industriale",
  "event.economy.industrial_accident.description": "Un grave incidente in un complesso chimico ha causato vittime e danni ambientali. Le immagini stanno facendo il giro del mondo.",
  "event.economy.industrial_accident.choice.compensate": "Risarcisci famiglie e comunità colpite",
  "event.economy.industrial_accident.choice.shift_blame": "Attribuisci la colpa al management privato",
  "event.economy.industrial_accident.choice.regulate": "Avvia una riforma normativa rigorosa",

  "event.intel.recruit_dissident.name": "Dissidente boreale",
  "event.intel.recruit_dissident.description": "Un alto funzionario boreale ha contattato in segreto la nostra ambasciata. Vuole defezionare e collaborare.",
  "event.intel.recruit_dissident.choice.recruit": "Reclutalo come asset operativo",
  "event.intel.recruit_dissident.choice.grant_asylum": "Concedigli asilo politico",
  "event.intel.recruit_dissident.choice.deny_entry": "Negagli l'ingresso per evitare incidenti",

  "victory.economic.name": "Vittoria economica",
  "victory.economic.description": "Porta Aurion tra le prime tre economie mondiali per PIL. Il denaro decide più di ogni esercito.",
  "victory.military.name": "Vittoria militare",
  "victory.military.description": "Controlla almeno dieci nazioni con la forza. Il mondo riconosce solo chi riesce a dominarlo.",
  "victory.scientific.name": "Vittoria scientifica",
  "victory.scientific.description": "Completa la prima colonia umana stabile su Marte. Aurion guiderà l'umanità tra le stelle.",
  "victory.diplomatic.name": "Vittoria diplomatica",
  "victory.diplomatic.description": "Costruisci un sistema di alleanze che copra almeno il 60% delle nazioni del mondo.",
  "victory.domination.name": "Dominio totale",
  "victory.domination.description": "Controlla 20 nazioni, oppure la prima economia mondiale insieme ad almeno 15 nazioni sotto la tua bandiera.",

  "difficulty.easy.name": "Facile",
  "difficulty.normal.name": "Normale",
  "difficulty.hard.name": "Difficile",
  "difficulty.ironMan.name": "Iron Man",

  "bloc.ascesa.western.name": "Patto di Auriana",
  "bloc.ascesa.eastern.name": "Sfera Borea",
  "bloc.ascesa.non-aligned.name": "Movimento dei Liberi",

  "un.ascesa.peacekeeping.title": "Mediazione del Concilio sulla regione contesa",
  "un.ascesa.peacekeeping.description": "Il Concilio delle Nazioni propone l'invio di una forza neutrale per separare i contendenti e congelare il fronte.",
  "un.ascesa.condemnation.tactical.title": "Condanna dell'uso di armi proibite",
  "un.ascesa.condemnation.tactical.description": "Risoluzione che condanna formalmente il ricorso ad armamenti tattici di distruzione di massa nel teatro di guerra.",
  "un.ascesa.condemnation.strategic.title": "Condanna dell'attacco strategico",
  "un.ascesa.condemnation.strategic.description": "Sessione d'emergenza del Concilio per condannare l'attacco strategico e valutare misure ritorsive comuni.",
  "un.ascesa.humanitarian.title": "Programma d'aiuto alle terre povere",
  "un.ascesa.humanitarian.description": "Sostegno coordinato alle popolazioni più fragili colpite da carestie, esodi e conflitti regionali.",
  "un.ascesa.condemnation.sanctions.title": "Mozione contro le sanzioni unilaterali",
  "un.ascesa.condemnation.sanctions.description": "Discussione formale sulla legittimità del regime di sanzioni imposto e sull'impatto sulle popolazioni civili.",
  "un.ascesa.climate.tension.title": "Patto di distensione del Concilio",
  "un.ascesa.climate.tension.description": "Quadro multilaterale per ridurre la tensione fra le sfere di influenza e prevenire un'escalation a catena.",
  "un.ascesa.climate.periodic.title": "Convenzione sull'equilibrio del mondo",
  "un.ascesa.climate.periodic.description": "Trattato periodico sul clima e l'uso delle risorse naturali, vincolante per tutti i firmatari del Concilio."
}
